{"_type":"export","__export_format":4,"__export_date":"2023-10-08T05:43:11.601Z","__export_source":"insomnia.desktop.app:v2023.5.5","resources":[{"_id":"req_df03a7147c24468da429853fa0950a34","parentId":"fld_9f954f7ef01140648bf87f36d83e2361","modified":1696742547281,"created":1696741093959,"url":"http://127.0.0.1:8000/api/management","name":"Registrar","description":"","method":"POST","body":{"mimeType":"application/json","text":"{\n\"titulo\":\"Escola\",\n\"descricao\":\"Trabalho feito com esforço e carinho\",\n\"data_inicio\":\"2023-09-01\",\n\"data_termino\": \"2023-09-15\",\n\"valor_projeto\":\"200.00\",\n\"status\":\"Finalizado\"\n}"},"parameters":[],"headers":[{"name":"Content-Type","value":"application/json"},{"name":"User-Agent","value":"Insomnia/2023.5.5"}],"authentication":{},"metaSortKey":-1696741093959,"isPrivate":false,"settingStoreCookies":true,"settingSendCookies":true,"settingDisableRenderRequestBody":false,"settingEncodeUrl":true,"settingRebuildPath":true,"settingFollowRedirects":"global","_type":"request"},{"_id":"fld_9f954f7ef01140648bf87f36d83e2361","parentId":"wrk_3f61c3aafe7b4c1aa6d5caba47234a27","modified":1696741145505,"created":1696741145505,"name":"Gestão","description":"","environment":{},"environmentPropertyOrder":null,"metaSortKey":-1696741145505,"_type":"request_group"},{"_id":"wrk_3f61c3aafe7b4c1aa6d5caba47234a27","parentId":null,"modified":1696741090543,"created":1696741090543,"name":"CRUD","description":"","scope":"collection","_type":"workspace"},{"_id":"req_a031d6543d3449f8ac605910eb8441e1","parentId":"fld_9f954f7ef01140648bf87f36d83e2361","modified":1696743209214,"created":1696741112616,"url":"http://127.0.0.1:8000/api/management/update","name":"Atualizar","description":"","method":"POST","body":{"mimeType":"application/json","text":"{\n\"id\":2,\n\"titulo\":\"Escola\",\n\"descricao\":\"Trabalho feito com esforço e carinho\",\n\"data_inicio\":\"2023-09-01\",\n\"data_termino\": \"2023-09-15\",\n\"valor_projeto\":\"200.00\",\n\"status\":\"Finalizado\"\n}"},"parameters":[],"headers":[{"name":"Content-Type","value":"application/json"},{"name":"User-Agent","value":"Insomnia/2023.5.5"}],"authentication":{},"metaSortKey":-1696741093958.0234,"isPrivate":false,"settingStoreCookies":true,"settingSendCookies":true,"settingDisableRenderRequestBody":false,"settingEncodeUrl":true,"settingRebuildPath":true,"settingFollowRedirects":"global","_type":"request"},{"_id":"req_bb3bc33f5059485ab8f1abf0ef3d504f","parentId":"fld_9f954f7ef01140648bf87f36d83e2361","modified":1696743135144,"created":1696741118882,"url":"http://127.0.0.1:8000/api/management/delete/1","name":"Deletar","description":"","method":"DELETE","body":{},"parameters":[],"headers":[{"name":"User-Agent","value":"Insomnia/2023.5.5"}],"authentication":{},"metaSortKey":-1696741093907.4375,"isPrivate":false,"settingStoreCookies":true,"settingSendCookies":true,"settingDisableRenderRequestBody":false,"settingEncodeUrl":true,"settingRebuildPath":true,"settingFollowRedirects":"global","_type":"request"},{"_id":"req_ce7455028630498690eacc0ab113fe53","parentId":"fld_9f954f7ef01140648bf87f36d83e2361","modified":1696743265405,"created":1696741123977,"url":"http://127.0.0.1:8000/api/management/find/2","name":"Pesquisar por ID","description":"","method":"GET","body":{},"parameters":[],"headers":[{"name":"User-Agent","value":"Insomnia/2023.5.5"}],"authentication":{},"metaSortKey":-1696741093857.4375,"isPrivate":false,"settingStoreCookies":true,"settingSendCookies":true,"settingDisableRenderRequestBody":false,"settingEncodeUrl":true,"settingRebuildPath":true,"settingFollowRedirects":"global","_type":"request"},{"_id":"req_d0371fc7215e4425a22f80486f20473f","parentId":"fld_9f954f7ef01140648bf87f36d83e2361","modified":1696743289257,"created":1696741124838,"url":"http://127.0.0.1:8000/api/management/find/title","name":"Pesquisar por título","description":"","method":"POST","body":{"mimeType":"application/json","text":"{\n\t\"titulo\":\"Es\"\n}"},"parameters":[],"headers":[{"name":"Content-Type","value":"application/json"},{"name":"User-Agent","value":"Insomnia/2023.5.5"}],"authentication":{},"metaSortKey":-1696741093957.7305,"isPrivate":false,"settingStoreCookies":true,"settingSendCookies":true,"settingDisableRenderRequestBody":false,"settingEncodeUrl":true,"settingRebuildPath":true,"settingFollowRedirects":"global","_type":"request"},{"_id":"env_e9a6a9c789f6af839b84d8b3c87967a8da9ba6be","parentId":"wrk_3f61c3aafe7b4c1aa6d5caba47234a27","modified":1696741090544,"created":1696741090544,"name":"Base Environment","data":{},"dataPropertyOrder":null,"color":null,"isPrivate":false,"metaSortKey":1696741090544,"_type":"environment"},{"_id":"jar_e9a6a9c789f6af839b84d8b3c87967a8da9ba6be","parentId":"wrk_3f61c3aafe7b4c1aa6d5caba47234a27","modified":1696741090545,"created":1696741090545,"name":"Default Jar","cookies":[],"_type":"cookie_jar"}]}